deferrer/__init__.py
deferrer/py.typed
deferrer/_core/__init__.py
deferrer/_core/_defer_scope.py
deferrer/_core/_deferred_actions.py
deferrer/_core/_defer/__init__.py
deferrer/_core/_defer/_mixed.py
deferrer/_core/_defer/_sugarful.py
deferrer/_core/_defer/_sugarless.py
deferrer/_utils/__init__.py
deferrer/_utils/_code_location.py
deferrer/_utils/_frame.py
deferrer/_utils/_opcode.py
deferrer-1.1.0.dist-info/licenses/LICENSE
deferrer-1.1.0.dist-info/METADATA
deferrer-1.1.0.dist-info/WHEEL
deferrer-1.1.0.dist-info/top_level.txt
deferrer-1.1.0.dist-info/RECORD
