Metadata-Version: 2.4
Name: deferrer
Version: 1.1.0
Summary: Fancy `defer` for Python >= 3.12 (partially supported in Python 3.11)
Author-email: Chris Fu <17433201@qq.com>
License: MIT License
Project-URL: Homepage, https://github.com/Azureblade3808/py-deferrer
Project-URL: Bug Tracker, https://github.com/Azureblade3808/py-deferrer/issues
Keywords: defer,sugar
Classifier: Programming Language :: Python
Classifier: Programming Language :: Python :: 3
Classifier: Programming Language :: Python :: 3.11
Classifier: Programming Language :: Python :: 3.12
Classifier: Programming Language :: Python :: 3.13
Classifier: Programming Language :: Python :: 3.14
Classifier: Programming Language :: Python :: Implementation :: CPython
Classifier: License :: OSI Approved :: MIT License
Classifier: Operating System :: OS Independent
Classifier: Intended Audience :: Developers
Classifier: Development Status :: 5 - Production/Stable
Requires-Python: <3.15,>=3.11
License-File: LICENSE
Dynamic: license-file
